apitaxdrivers/Ansible.py
apitaxdrivers/AnsibleCommands.py
apitaxdrivers/ApitaxInfo.py
apitaxdrivers/ApitaxTests.py
apitaxdrivers/BasicAuth.py
apitaxdrivers/BasicGit.py
apitaxdrivers/Github.py
apitaxdrivers/Openstack.py
apitaxdrivers/Vsrx.py
apitaxdrivers/__init__.py
apitaxdrivers/commandtax/AnsibleCommands.py
apitaxdrivers/commandtax/ApitaxInfoCommands.py
apitaxdrivers/commandtax/ApitaxTestsCommands.py
apitaxdrivers/commandtax/__init__.py
apitaxdrivers/commandtax/apitaxinfo/__init__.py
apitaxdrivers/commandtax/apitaxtests/Domains.py
apitaxdrivers/commandtax/apitaxtests/Projects.py
apitaxdrivers/commandtax/apitaxtests/Tests.py
apitaxdrivers/commandtax/apitaxtests/__init__.py
apitaxdrivers/integrations/BasicGit.py
apitaxdrivers/integrations/Git.py
apitaxdrivers/integrations/Github.py
apitaxdrivers/integrations/Gitlab.py
apitaxdrivers/integrations/__init__.py
apitaxdrivers/scriptax/__init__.py
apitaxdrivers-0.0.12.dist-info/LICENSE
apitaxdrivers-0.0.12.dist-info/METADATA
apitaxdrivers-0.0.12.dist-info/WHEEL
apitaxdrivers-0.0.12.dist-info/top_level.txt
apitaxdrivers-0.0.12.dist-info/RECORD
