Metadata-Version: 2.1
Name: apitaxdrivers
Version: 0.0.12
Summary: A set of example and micro drivers which can be used as the basis of more robust API drivers or combined together to form a robust application.
Home-page: https://github.com/ShawnClake/Apitax
Author: Shawn Clake
Author-email: shawn.clake@gmail.com
License: UNKNOWN
Keywords: restful,api,commandtax,scriptax,apitax,drivers,plugins
Platform: UNKNOWN
Classifier: Programming Language :: Python :: 3
Classifier: License :: OSI Approved :: MIT License
Classifier: Operating System :: OS Independent
Requires-Dist: requests
Requires-Dist: python-gitlab
Requires-Dist: pygithub
Requires-Dist: gitpython
Requires-Dist: apitaxcore (==3.0.6)
Requires-Dist: commandtax (==0.0.8)
Requires-Dist: scriptax (==0.0.5)
